{
    "robot_specs": {
        "reach": 900,
        "payload": 6,
        "max_tcp_speed": 0.3,
        "default_travel_speed": 0.0099,
        "default_weld_speed": 0.0099,
        "min_weld_speed": 0.003,
        "max_weld_speed": 0.0099
    },
    "prusa_origin": {"x": 0, "y": 0, "z": 0},
    "taught_start_position": {
        "enabled": true,
        "safety_delay_seconds": 7.5
    },
    "waam_params": {
        "delay_type": "time",  
        "welding_strategy": "alternating",
        "travel_z_lift": 10,
        "travel_stabilization_delay": 5.0,
        "pre_weld_delay": 0.0,
        "arc_strike_delay": 0.0,
        "arc_stabilization": 0.0,
        "arc_off_delay": 0.0,
        "post_weld_delay": 0.0,
        "inter_layer_delay": 39.8,
        "layer_height": 2.0,
        "start_speed_factor": 0.4,
        "end_speed_factor": 0.5,
        "ramp_distance": 5.0,
        "max_blend_distance": 2.0,
        "min_blend_distance": 0.1,
        "corner_angle_threshold": 15,
        "min_extrusion_threshold": 0.01,
        "torch_output": 1,
        "retraction_max_distance": 10,
        "apo_cdis": 0.25,
        "auto_prusa_origin": false,
        "weaving_enabled": true,
        "weaving_amplitude": 2.25,
        "weaving_frequency": 0.17, 
        "weaving_points_per_cycle": 4
    }
}